setup.py
distribution_simba/Binomialdistribution.py
distribution_simba/Gaussiandistribution.py
distribution_simba/Generaldistribution.py
distribution_simba/__init__.py
distribution_simba.egg-info/PKG-INFO
distribution_simba.egg-info/SOURCES.txt
distribution_simba.egg-info/dependency_links.txt
distribution_simba.egg-info/not-zip-safe
distribution_simba.egg-info/top_level.txt