Metadata-Version: 1.0
Name: distribution-simba
Version: 0.1
Summary: Gaussian and Binomial distributions
Home-page: UNKNOWN
Author: Sudhanshu Kumar
Author-email: UNKNOWN
License: UNKNOWN
Platform: UNKNOWN
